{
  "id": "centered_cta",
  "type": "SharedSlice",
  "name": "CenteredCta",
  "description": "CenteredCta",
  "variations": [
    {
      "id": "default",
      "name": "Default",
      "docURL": "...",
      "version": "initial",
      "description": "Default",
      "imageUrl": "",
      "primary": {
        "bg_color": {
          "type": "Select",
          "config": {
            "label": "BG Color",
            "placeholder": "",
            "options": [
              "Slate",
              "White",
              "Gray"
            ],
            "default_value": "Slate"
          }
        },
        "number": {
          "type": "Text",
          "config": {
            "label": "Numbered Item",
            "placeholder": ""
          }
        },
        "heading": {
          "type": "Text",
          "config": {
            "label": "Heading",
            "placeholder": ""
          }
        },
        "body": {
          "type": "StructuredText",
          "config": {
            "label": "Body",
            "placeholder": "",
            "allowTargetBlank": true,
            "multi": "paragraph,preformatted,heading1,heading2,heading3,heading4,heading5,heading6,strong,em,hyperlink,image,embed,list-item,o-list-item,rtl"
          }
        },
        "image": {
          "type": "Image",
          "config": {
            "label": "Image",
            "constraint": {},
            "thumbnails": []
          }
        },
        "buttons": {
          "type": "Group",
          "config": {
            "label": "Buttons",
            "repeat": true,
            "fields": {
              "button_link": {
                "type": "Link",
                "config": {
                  "label": "Button Link",
                  "placeholder": "",
                  "allowTargetBlank": false,
                  "select": null
                }
              },
              "button_label": {
                "type": "Text",
                "config": {
                  "label": "Link Text",
                  "placeholder": ""
                }
              },
              "button_cta": {
                "type": "Boolean",
                "config": {
                  "label": "CTA",
                  "placeholder_false": "false",
                  "placeholder_true": "true",
                  "default_value": false
                }
              }
            }
          }
        }
      },
      "items": {}
    }
  ]
}